microlux/__init__.py
microlux/basic_function.py
microlux/countour.py
microlux/error_estimator.py
microlux/limb_darkening.py
microlux/linear_sum_assignment.py
microlux/model.py
microlux/polynomial_solver.py
microlux/solution.py
microlux/utils.py
microlux-0.2.0.dist-info/licenses/LICENSE
microlux-0.2.0.dist-info/METADATA
microlux-0.2.0.dist-info/WHEEL
microlux-0.2.0.dist-info/top_level.txt
microlux-0.2.0.dist-info/RECORD
