Metadata-Version: 2.4
Name: microlux
Version: 0.2.0
Summary: A JAX-based package for microlensing binary lens
Author-email: Haibin Ren <rhb23@mails.tsinghua.edu.cn>
License: MIT License
Project-URL: repository, https://github.com/CoastEgo/microlux
Keywords: jax,microlensing,binary lens
Classifier: License :: OSI Approved :: MIT License
Classifier: Programming Language :: Python :: 3
Requires-Python: >=3.9
License-File: LICENSE
Requires-Dist: jax>=0.4.28
Requires-Dist: numpy
Requires-Dist: scipy
Dynamic: license-file
